jules_cli/__init__.py
jules_cli/banner.py
jules_cli/cache.py
jules_cli/cli.py
jules_cli/db.py
jules_cli/state.py
jules_cli/commands/__init__.py
jules_cli/commands/apply.py
jules_cli/commands/auth.py
jules_cli/commands/auto.py
jules_cli/commands/commit.py
jules_cli/commands/config.py
jules_cli/commands/doctor.py
jules_cli/commands/history.py
jules_cli/commands/hooks.py
jules_cli/commands/init.py
jules_cli/commands/interact.py
jules_cli/commands/plan.py
jules_cli/commands/pr.py
jules_cli/commands/refactor.py
jules_cli/commands/session.py
jules_cli/commands/stage.py
jules_cli/commands/suggest.py
jules_cli/commands/task.py
jules_cli/commands/testgen.py
jules_cli/commands/upgrade.py
jules_cli/commands/workspace.py
jules_cli/core/__init__.py
jules_cli/core/api.py
jules_cli/git/__init__.py
jules_cli/git/vcs.py
jules_cli/patch/__init__.py
jules_cli/patch/apply.py
jules_cli/patch/resolver.py
jules_cli/testing/__init__.py
jules_cli/testing/runner.py
jules_cli/tui/__init__.py
jules_cli/tui/app.py
jules_cli/utils/__init__.py
jules_cli/utils/branch.py
jules_cli/utils/commands.py
jules_cli/utils/config.py
jules_cli/utils/decorators.py
jules_cli/utils/environment.py
jules_cli/utils/exceptions.py
jules_cli/utils/ignore.py
jules_cli/utils/logging.py
jules_cli/utils/output.py
jules_cli-17.0.1.dist-info/METADATA
jules_cli-17.0.1.dist-info/WHEEL
jules_cli-17.0.1.dist-info/entry_points.txt
jules_cli-17.0.1.dist-info/top_level.txt
jules_cli-17.0.1.dist-info/RECORD
