Metadata-Version: 2.4
Name: jules-cli
Version: 17.0.1
Summary: A developer CLI for Jules API automation
Author: dhruv13x
Requires-Python: >=3.8
Requires-Dist: requests
Requires-Dist: typer>=0.9.0
Requires-Dist: python-slugify>=8.0.0
Requires-Dist: anthropic>=0.18.0
Requires-Dist: toml>=0.10.0
Requires-Dist: PyYAML>=6.0
Requires-Dist: keyring>=24.0.0
Requires-Dist: textual>=0.50.0
Provides-Extra: dev
Requires-Dist: pytest>=8.0.0; extra == "dev"
Requires-Dist: pytest-cov>=5.0.0; extra == "dev"
Requires-Dist: pytest-timeout>=2.2.0; extra == "dev"
Requires-Dist: pytest-json-report>=1.5.0; extra == "dev"
Requires-Dist: pytest-asyncio>=0.23.0; extra == "dev"
Requires-Dist: pytest-mock>=3.10.0; extra == "dev"
Requires-Dist: pyfakefs>=5.0.0; extra == "dev"
Requires-Dist: ruff>=0.6.0; extra == "dev"
Requires-Dist: black>=24.3.0; extra == "dev"
Requires-Dist: mypy>=1.11.0; extra == "dev"
Requires-Dist: PyYAML>=6.0; extra == "dev"
Requires-Dist: types-PyYAML>=6.0; extra == "dev"
